mathify/__init__.py
mathify/algebra.py
mathify/arithmetic.py
mathify-0.1.0.dist-info/LICENSE
mathify-0.1.0.dist-info/METADATA
mathify-0.1.0.dist-info/WHEEL
mathify-0.1.0.dist-info/entry_points.txt
mathify-0.1.0.dist-info/top_level.txt
mathify-0.1.0.dist-info/RECORD
