Metadata-Version: 2.1
Name: mathify
Version: 0.1.0
Summary: A package for mathematical utilities and functions
Home-page: https://github.com/none/mathify
Author: David Warner
Author-email: kaboom31@example.com
License: UNKNOWN
Platform: UNKNOWN
Classifier: Programming Language :: Python :: 3
Classifier: License :: OSI Approved :: MIT License
Classifier: Operating System :: OS Independent
Requires-Python: >=3.6
